basecrawler/__init__.py
basecrawler/basecrawler.py
basecrawler-0.1.20.dist-info/LICENSE
basecrawler-0.1.20.dist-info/METADATA
basecrawler-0.1.20.dist-info/WHEEL
basecrawler-0.1.20.dist-info/top_level.txt
basecrawler-0.1.20.dist-info/RECORD
