Metadata-Version: 2.1
Name: basecrawler
Version: 0.1.20
Summary: This is the crawler libray
Home-page: https://github.com/ever391/basecrawler
Author: ever391
Author-email: smart.jin@foxmail.com
License: MIT
Platform: UNKNOWN
Classifier: Intended Audience :: Developers
Classifier: License :: OSI Approved :: MIT License
Classifier: Operating System :: OS Independent
Classifier: Programming Language :: Python
Requires-Dist: requests
Requires-Dist: bs4
Requires-Dist: selenium
Requires-Dist: Pillow
Requires-Dist: lxml
Requires-Dist: jieba
